<indicator id="pyj6tScZqmEdfXahiCHkPfA" closestAboveZero="1.0" closestBelowZero="0.0" min="0.0" max="368.0" firstTime="1990" lastTime="2005" scale="lin" dataCollectionUrl="http://spreadsheets.google.com/pub?key=pyj6tScZqmEdfXahiCHkPfA" providerUrl="http://data.un.org" providerSourceName="UN Statistics Division">
  <data>
    <t1 m="i20,5.0,10.0,1990" d="5.0,n4,7.0,8.0,9.0,9.0,10.0,10.0,9.0,8.0,8.0,8.0,8.0"/>
    <t1 m="i176,47.0,80.0,1990" d="80.0,n4,74.0,78.0,76.0,74.0,70.0,58.0,54.0,52.0,49.0,48.0,47.0"/>
    <t1 m="i150,7.0,11.0,1990" d="11.0,n4,11.0,11.0,11.0,11.0,10.0,10.0,10.0,9.0,9.0,9.0,7.0"/>
    <t1 m="i120,8.0,20.0,1990" d="8.0,n4,11.0,14.0,16.0,18.0,19.0,20.0,20.0,19.0,19.0,18.0,18.0"/>
    <t1 m="i62,14.0,29.0,1990" d="29.0,n4,26.0,22.0,24.0,24.0,22.0,22.0,21.0,18.0,16.0,16.0,14.0"/>
    <t1 m="i1,35.0,69.0,1990" d="69.0,n4,65.0,64.0,61.0,57.0,56.0,52.0,49.0,45.0,43.0,44.0,35.0"/>
    <t1 m="i161,8.0,23.0,1990" d="23.0,n4,16.0,15.0,13.0,12.0,12.0,11.0,9.0,10.0,8.0,8.0,8.0"/>
    <t1 m="i95,58.0,112.0,1990" d="112.0,n4,97.0,94.0,91.0,86.0,81.0,78.0,74.0,69.0,65.0,63.0,58.0"/>
    <t1 m="i76,1.0,2.0,1990" d="2.0,n4,2.0,2.0,2.0,2.0,2.0,2.0,2.0,1.0,1.0,1.0,1.0"/>
    <t1 m="i180,1.0,4.0,1990" d="4.0,n4,2.0,2.0,1.0,1.0,1.0,1.0,1.0,1.0,1.0,1.0,1.0"/>
    <t1 m="i38,35.0,45.0,1990" d="44.0,n4,43.0,43.0,43.0,43.0,44.0,44.0,35.0,45.0,45.0,45.0,37.0"/>
    <t1 m="i60,65.0,129.0,1990" d="127.0,n4,129.0,73.0,65.0,92.0,86.0,95.0,93.0,117.0,120.0,126.0,128.0"/>
    <t1 m="i39,0.0,1.0,1990" d="1.0,n4,1.0,1.0,1.0,1.0,1.0,1.0,1.0,1.0,1.0,0.0,0.0"/>
    <t1 m="i122,5.0,12.0,1990" d="5.0,n4,9.0,11.0,12.0,12.0,12.0,12.0,12.0,12.0,11.0,10.0,9.0"/>
    <t1 m="i18,47.0,76.0,1990" d="76.0,n4,66.0,63.0,61.0,59.0,57.0,57.0,56.0,55.0,52.0,51.0,47.0"/>
    <t1 m="i27,6.0,15.0,1990" d="15.0,n4,13.0,13.0,12.0,11.0,10.0,9.0,8.0,8.0,8.0,6.0,8.0"/>
    <t1 m="i172,3.0,9.0,1990" d="9.0,n4,8.0,7.0,8.0,7.0,7.0,7.0,5.0,4.0,4.0,3.0,4.0"/>
    <t1 m="i250,2.0,3.0,1990" d="3.0,n4,3.0,2.0,2.0,2.0,2.0,2.0,2.0,2.0,2.0,2.0,2.0"/>
    <t1 m="i242,10.0,16.0,1990" d="10.0,n4,11.0,10.0,11.0,11.0,12.0,13.0,14.0,15.0,15.0,16.0,16.0"/>
    <t1 m="i34,36.0,83.0,1990" d="36.0,n4,57.0,60.0,61.0,72.0,67.0,70.0,75.0,80.0,82.0,81.0,83.0"/>
    <t1 m="i94,9.0,25.0,1990" d="9.0,n4,14.0,15.0,16.0,18.0,19.0,20.0,21.0,22.0,24.0,24.0,25.0"/>
    <t1 m="i115,49.0,115.0,1990" d="115.0,n4,96.0,83.0,82.0,65.0,65.0,64.0,71.0,68.0,57.0,51.0,49.0"/>
    <t1 m="i143,2.0,10.0,1990" d="10.0,n4,7.0,7.0,6.0,6.0,5.0,4.0,3.0,3.0,3.0,3.0,2.0"/>
    <t1 m="i37,0.0,1.0,1990" d="1.0,n4,1.0,1.0,1.0,1.0,1.0,1.0,1.0,1.0,0.0,0.0,0.0"/>
    <t1 m="i121,24.0,37.0,1990" d="37.0,n4,33.0,30.0,29.0,28.0,27.0,28.0,27.0,27.0,26.0,25.0,24.0"/>
    <t1 m="i138,31.0,68.0,1990" d="68.0,n4,56.0,55.0,54.0,47.0,47.0,47.0,43.0,43.0,41.0,31.0,32.0"/>
    <t1 m="i100,0.0,1.0,1990" d="1.0,n4,0.0,0.0,0.0,0.0,0.0,0.0,0.0,0.0,0.0,0.0,0.0"/>
    <t1 m="i49,32.0,78.0,1990" d="32.0,n4,54.0,56.0,62.0,62.0,67.0,72.0,74.0,78.0,76.0,74.0,73.0"/>
    <t1 m="i19,1.0,3.0,1990" d="3.0,n4,3.0,3.0,3.0,3.0,3.0,2.0,2.0,2.0,2.0,1.0,1.0"/>
    <t1 m="i123,1.0,4.0,1990" d="4.0,n4,3.0,3.0,2.0,2.0,2.0,2.0,2.0,1.0,1.0,1.0,1.0"/>
    <t1 m="i124,31.0,191.0,1990" d="31.0,n4,49.0,52.0,56.0,66.0,191.0,81.0,85.0,95.0,95.0,86.0,107.0"/>
    <t1 m="i66,8.0,17.0,1990" d="17.0,n4,13.0,14.0,12.0,12.0,11.0,11.0,10.0,10.0,9.0,9.0,8.0"/>
    <t1 m="i30,2.0,3.0,1990" d="3.0,n4,3.0,3.0,3.0,3.0,3.0,3.0,3.0,3.0,3.0,2.0,3.0"/>
    <t1 m="i205,2.0,5.0,1990" d="5.0,n4,4.0,4.0,4.0,4.0,3.0,3.0,3.0,3.0,2.0,2.0,2.0"/>
    <t1 m="i149,1.0,2.0,1990" d="2.0,n4,2.0,2.0,2.0,2.0,2.0,2.0,2.0,2.0,1.0,2.0,1.0"/>
    <t1 m="i33,42.0,59.0,1990" d="45.0,n4,42.0,47.0,42.0,44.0,47.0,48.0,47.0,48.0,49.0,54.0,59.0"/>
    <t1 m="i147,23.0,51.0,1990" d="51.0,n4,45.0,38.0,39.0,37.0,36.0,36.0,33.0,31.0,32.0,25.0,23.0"/>
    <t1 m="i90,13.0,16.0,1990" d="16.0,n4,14.0,14.0,14.0,14.0,14.0,14.0,14.0,13.0,13.0,13.0,13.0"/>
    <t1 m="i57,1.0,2.0,1990" d="2.0,n4,2.0,2.0,2.0,2.0,2.0,2.0,2.0,1.0,1.0,1.0,1.0"/>
    <t1 m="i253,10.0,16.0,1990" d="16.0,n4,16.0,15.0,15.0,14.0,13.0,13.0,12.0,12.0,12.0,11.0,10.0"/>
    <t1 m="i224,85.0,126.0,1990" d="126.0,n4,121.0,121.0,121.0,121.0,121.0,121.0,121.0,96.0,98.0,85.0,88.0"/>
    <t1 m="i65,3.0,4.0,1990" d="4.0,n4,4.0,4.0,4.0,4.0,4.0,4.0,3.0,3.0,3.0,3.0,3.0"/>
    <t1 m="i184,10.0,23.0,1990" d="10.0,n4,16.0,18.0,19.0,22.0,21.0,23.0,23.0,22.0,21.0,21.0,20.0"/>
    <t1 m="i159,1.0,1.0,1990" d="1.0,n4,1.0,1.0,1.0,1.0,1.0,1.0,1.0,1.0,1.0,1.0,1.0"/>
    <t1 m="i7,28.0,73.0,1990" d="61.0,n4,67.0,68.0,50.0,57.0,53.0,73.0,47.0,32.0,28.0,34.0,36.0"/>
    <t1 m="i103,3.0,5.0,1990" d="4.0,n4,5.0,5.0,4.0,4.0,4.0,4.0,3.0,3.0,3.0,3.0,3.0"/>
    <t1 m="i85,2.0,4.0,1990" d="4.0,n4,3.0,3.0,3.0,3.0,3.0,3.0,2.0,2.0,2.0,2.0,2.0"/>
    <t1 m="i135,3.0,8.0,1990" d="8.0,n4,5.0,5.0,7.0,6.0,6.0,7.0,6.0,6.0,5.0,4.0,3.0"/>
    <t1 m="i223,19.0,27.0,1990" d="27.0,n4,27.0,27.0,26.0,25.0,23.0,22.0,20.0,20.0,19.0,19.0,19.0"/>
    <t1 m="i236,6.0,14.0,1990" d="6.0,n4,7.0,8.0,9.0,11.0,11.0,12.0,13.0,13.0,14.0,14.0,14.0"/>
    <t1 m="i31,4.0,12.0,1990" d="12.0,n4,11.0,10.0,10.0,10.0,4.0,4.0,4.0,4.0,5.0,5.0,5.0"/>
    <t1 m="i108,1.0,1.0,1990" d="1.0,n4,1.0,1.0,1.0,1.0,1.0,1.0,1.0,1.0,1.0,1.0,1.0"/>
    <t1 m="i104,8.0,12.0,1990" d="12.0,n4,12.0,8.0,8.0,8.0,8.0,10.0,10.0,9.0,9.0,10.0,11.0"/>
    <t1 m="i227,2.0,6.0,1990" d="6.0,n4,5.0,3.0,4.0,2.0,4.0,3.0,5.0,3.0,3.0,4.0,3.0"/>
    <t1 m="i145,9.0,21.0,1990" d="9.0,n4,12.0,14.0,16.0,18.0,19.0,20.0,21.0,21.0,20.0,19.0,19.0"/>
    <t1 m="i144,14.0,33.0,1990" d="33.0,n4,24.0,23.0,27.0,26.0,25.0,19.0,19.0,17.0,16.0,15.0,14.0"/>
    <t1 m="i173,46.0,68.0,1990" d="68.0,n4,64.0,66.0,64.0,57.0,60.0,59.0,58.0,53.0,51.0,47.0,46.0"/>
    <t1 m="i92,31.0,52.0,1990" d="31.0,n4,35.0,35.0,37.0,39.0,40.0,42.0,44.0,45.0,47.0,49.0,52.0"/>
    <t1 m="i56,0.0,1.0,1990" d="1.0,n4,1.0,1.0,1.0,1.0,1.0,1.0,0.0,1.0,0.0,0.0,0.0"/>
    <t1 m="i59,1.0,1.0,1990" d="1.0,n4,1.0,1.0,1.0,1.0,1.0,1.0,1.0,1.0,1.0,1.0,1.0"/>
    <t1 m="i119,2.0,4.0,1990" d="4.0,n4,4.0,4.0,3.0,3.0,3.0,3.0,3.0,3.0,3.0,3.0,2.0"/>
    <t1 m="i83,48.0,60.0,1990" d="60.0,n4,57.0,57.0,53.0,53.0,53.0,51.0,49.0,49.0,49.0,49.0,48.0"/>
    <t1 m="i170,37.0,49.0,1990" d="49.0,n4,49.0,49.0,49.0,48.0,49.0,48.0,48.0,45.0,43.0,40.0,37.0"/>
    <t1 m="i51,2.0,5.0,1990" d="5.0,n4,4.0,4.0,4.0,3.0,3.0,3.0,2.0,3.0,3.0,3.0,3.0"/>
    <t1 m="i79,45.0,81.0,1990" d="46.0,n4,45.0,51.0,54.0,61.0,66.0,81.0,50.0,61.0,59.0,59.0,65.0"/>
    <t1 m="i11,6.0,12.0,1990" d="6.0,n4,8.0,9.0,9.0,10.0,11.0,12.0,12.0,12.0,11.0,11.0,10.0"/>
    <t1 m="i67,18.0,69.0,1990" d="18.0,n4,30.0,34.0,36.0,37.0,39.0,41.0,64.0,67.0,69.0,47.0,47.0"/>
    <t1 m="i54,6.0,12.0,1990" d="12.0,n4,10.0,10.0,10.0,9.0,9.0,7.0,7.0,7.0,7.0,7.0,6.0"/>
    <t1 m="i36,19.0,42.0,1990" d="19.0,n4,34.0,37.0,40.0,41.0,42.0,42.0,42.0,39.0,31.0,28.0,23.0"/>
    <t1 m="i53,34.0,107.0,1990" d="34.0,n4,59.0,65.0,72.0,77.0,83.0,91.0,107.0,99.0,100.0,98.0,99.0"/>
    <t1 m="i256,45.0,213.0,1990" d="45.0,n4,155.0,190.0,213.0,137.0,138.0,151.0,150.0,144.0,158.0,132.0,130.0"/>
    <t1 m="i217,0.0,1.0,1990" d="1.0,n4,1.0,1.0,1.0,1.0,1.0,1.0,0.0,0.0,0.0,1.0,1.0"/>
    <t1 m="i70,4.0,10.0,1990" d="4.0,n4,7.0,8.0,9.0,10.0,10.0,10.0,9.0,8.0,8.0,7.0,6.0"/>
    <t1 m="i163,27.0,78.0,1990" d="27.0,n4,50.0,54.0,59.0,63.0,66.0,70.0,74.0,78.0,78.0,76.0,76.0"/>
    <t1 m="i191,4.0,6.0,1990" d="6.0,n4,6.0,6.0,6.0,5.0,6.0,5.0,5.0,5.0,4.0,5.0,5.0"/>
    <t1 m="i26,31.0,51.0,1990" d="51.0,n4,45.0,38.0,38.0,37.0,36.0,35.0,34.0,33.0,33.0,32.0,31.0"/>
    <t1 m="i206,23.0,65.0,1990" d="65.0,n4,47.0,40.0,37.0,36.0,34.0,32.0,31.0,30.0,28.0,25.0,23.0"/>
    <t1 m="i125,35.0,75.0,1990" d="35.0,n4,58.0,56.0,60.0,60.0,63.0,71.0,74.0,68.0,75.0,65.0,70.0"/>
    <t1 m="i232,8.0,14.0,1990" d="10.0,n4,8.0,9.0,11.0,13.0,14.0,13.0,13.0,12.0,12.0,11.0,10.0"/>
    <t1 m="i233,2.0,4.0,1990" d="4.0,n4,4.0,4.0,4.0,4.0,2.0,2.0,4.0,3.0,3.0,3.0,3.0"/>
    <t1 m="i114,22.0,140.0,1990" d="22.0,n4,49.0,56.0,68.0,76.0,87.0,101.0,105.0,116.0,124.0,130.0,140.0"/>
    <t1 m="i131,5.0,11.0,1990" d="11.0,n4,10.0,10.0,9.0,9.0,8.0,7.0,6.0,6.0,5.0,5.0,5.0"/>
    <t1 m="i78,4.0,17.0,1990" d="17.0,n4,11.0,7.0,6.0,6.0,5.0,6.0,6.0,5.0,5.0,4.0,4.0"/>
    <t1 m="i175,20.0,37.0,1990" d="37.0,n4,27.0,34.0,29.0,24.0,28.0,27.0,25.0,24.0,23.0,22.0,20.0"/>
    <t1 m="i61,2.0,3.0,1990" d="3.0,n4,3.0,3.0,2.0,3.0,3.0,3.0,3.0,3.0,3.0,3.0,3.0"/>
    <t1 m="i117,10.0,12.0,1990" d="10.0,n4,10.0,10.0,10.0,10.0,10.0,12.0,10.0,11.0,11.0,11.0,11.0"/>
    <t1 m="i133,62.0,104.0,1990" d="62.0,n4,93.0,91.0,97.0,98.0,98.0,104.0,97.0,102.0,99.0,96.0,98.0"/>
    <t1 m="i230,2.0,3.0,1990" d="3.0,n4,3.0,3.0,3.0,3.0,3.0,2.0,2.0,3.0,3.0,3.0,3.0"/>
    <t1 m="i44,16.0,24.0,1990" d="24.0,n4,22.0,21.0,20.0,20.0,20.0,20.0,19.0,19.0,18.0,17.0,16.0"/>
    <t1 m="i195,27.0,38.0,1990" d="38.0,n4,32.0,32.0,31.0,30.0,30.0,30.0,29.0,29.0,28.0,28.0,27.0"/>
    <t1 m="i50,34.0,98.0,1990" d="34.0,n4,53.0,83.0,88.0,71.0,98.0,47.0,54.0,55.0,76.0,68.0,69.0"/>
    <t1 m="i80,38.0,63.0,1990" d="39.0,n4,39.0,39.0,39.0,38.0,60.0,62.0,63.0,42.0,44.0,44.0,46.0"/>
    <t1 m="i235,56.0,110.0,1990" d="56.0,n4,110.0,107.0,81.0,83.0,80.0,86.0,88.0,93.0,96.0,92.0,91.0"/>
    <t1 m="i201,3.0,9.0,1990" d="9.0,n4,7.0,5.0,4.0,5.0,7.0,5.0,4.0,4.0,5.0,3.0,5.0"/>
    <t1 m="i225,91.0,104.0,1990" d="91.0,n4,92.0,93.0,101.0,98.0,99.0,100.0,101.0,104.0,101.0,101.0,101.0"/>
    <t1 m="i213,60.0,66.0,1990" d="60.0,n4,64.0,65.0,66.0,61.0,62.0,61.0,63.0,61.0,62.0,63.0,65.0"/>
    <t1 m="i137,1.0,1.0,1990" d="1.0,n4,1.0,1.0,1.0,1.0,1.0,1.0,1.0,1.0,1.0,1.0,1.0"/>
    <t1 m="i16,5.0,12.0,1990" d="12.0,n4,10.0,10.0,9.0,9.0,7.0,6.0,5.0,7.0,7.0,6.0,6.0"/>
    <t1 m="i35,87.0,112.0,1990" d="112.0,n4,109.0,111.0,108.0,105.0,103.0,102.0,101.0,96.0,93.0,91.0,87.0"/>
    <t1 m="i229,1.0,2.0,1990" d="2.0,n4,2.0,2.0,2.0,2.0,2.0,2.0,2.0,2.0,1.0,1.0,1.0"/>
    <t1 m="i255,114.0,227.0,1990" d="114.0,n4,192.0,198.0,206.0,208.0,215.0,211.0,227.0,139.0,129.0,116.0,118.0"/>
    <t1 m="i21,1.0,2.0,1990" d="2.0,n4,2.0,2.0,2.0,2.0,2.0,2.0,2.0,2.0,1.0,1.0,1.0"/>
    <t1 m="i8,4.0,5.0,1990" d="5.0,n4,5.0,5.0,5.0,5.0,5.0,5.0,5.0,5.0,5.0,5.0,4.0"/>
    <t1 m="i179,3.0,7.0,1990" d="7.0,n4,6.0,6.0,6.0,5.0,5.0,5.0,4.0,4.0,4.0,4.0,3.0"/>
    <t1 m="i222,37.0,79.0,1990" d="37.0,n4,60.0,64.0,69.0,70.0,72.0,76.0,76.0,79.0,77.0,75.0,75.0"/>
    <t1 m="i136,71.0,85.0,1990" d="85.0,n4,78.0,77.0,76.0,75.0,75.0,75.0,74.0,73.0,72.0,72.0,71.0"/>
    <t1 m="i64,27.0,45.0,1990" d="45.0,n4,38.0,37.0,33.0,35.0,34.0,33.0,32.0,29.0,28.0,27.0,27.0"/>
    <t1 m="i102,41.0,91.0,1990" d="91.0,n4,75.0,72.0,70.0,67.0,63.0,61.0,59.0,53.0,50.0,46.0,41.0"/>
    <t1 m="i129,1.0,2.0,1990" d="2.0,n4,2.0,2.0,2.0,2.0,1.0,1.0,1.0,1.0,1.0,1.0,1.0"/>
    <t1 m="i43,1.0,6.0,1990" d="6.0,n4,4.0,3.0,3.0,3.0,3.0,2.0,2.0,2.0,2.0,1.0,1.0"/>
    <t1 m="i17,4.0,7.0,1990" d="7.0,n4,7.0,7.0,6.0,6.0,6.0,5.0,5.0,5.0,4.0,4.0,4.0"/>
    <t1 m="i74,3.0,7.0,1990" d="7.0,n4,5.0,5.0,5.0,5.0,4.0,5.0,4.0,4.0,3.0,4.0,4.0"/>
    <t1 m="i130,6.0,12.0,1990" d="12.0,n4,10.0,6.0,6.0,7.0,7.0,7.0,8.0,9.0,10.0,10.0,9.0"/>
    <t1 m="i164,3.0,13.0,1990" d="13.0,n4,11.0,8.0,11.0,10.0,8.0,10.0,10.0,3.0,9.0,9.0,9.0"/>
    <t1 m="i202,57.0,111.0,1990" d="57.0,n4,72.0,70.0,75.0,79.0,83.0,88.0,91.0,96.0,101.0,106.0,111.0"/>
    <t1 m="i193,2.0,5.0,1990" d="5.0,n4,4.0,4.0,4.0,5.0,3.0,3.0,4.0,2.0,3.0,3.0,3.0"/>
    <t1 m="i246,4.0,6.0,1990" d="6.0,n4,6.0,5.0,5.0,5.0,5.0,5.0,4.0,4.0,4.0,4.0,4.0"/>
    <t1 m="i169,1.0,2.0,1990" d="2.0,n4,1.0,1.0,1.0,1.0,1.0,1.0,1.0,1.0,1.0,1.0,1.0"/>
    <t1 m="i231,5.0,9.0,1990" d="9.0,n4,7.0,7.0,7.0,7.0,6.0,5.0,5.0,5.0,5.0,5.0,5.0"/>
    <t1 m="i162,34.0,38.0,1990" d="36.0,n4,38.0,38.0,35.0,34.0,35.0,34.0,35.0,35.0,34.0,35.0,35.0"/>
    <t1 m="i98,6.0,11.0,1990" d="11.0,n4,8.0,8.0,8.0,8.0,7.0,7.0,7.0,7.0,7.0,7.0,6.0"/>
    <t1 m="i157,2.0,2.0,1990" d="2.0,n4,2.0,2.0,2.0,2.0,2.0,2.0,2.0,2.0,2.0,2.0,2.0"/>
    <t1 m="i89,3.0,11.0,1990" d="11.0,n4,10.0,9.0,9.0,9.0,9.0,5.0,4.0,4.0,7.0,6.0,3.0"/>
    <t1 m="i41,25.0,78.0,1990" d="25.0,n4,41.0,49.0,58.0,62.0,56.0,59.0,63.0,68.0,78.0,73.0,70.0"/>
    <t1 m="i151,34.0,128.0,1990" d="34.0,n4,68.0,78.0,88.0,98.0,106.0,115.0,122.0,126.0,128.0,126.0,124.0"/>
    <t1 m="i23,16.0,18.0,1990" d="16.0,n4,16.0,17.0,17.0,17.0,16.0,16.0,16.0,17.0,18.0,17.0,17.0"/>
    <t1 m="i116,13.0,59.0,1990" d="59.0,n4,57.0,57.0,57.0,57.0,57.0,35.0,33.0,18.0,15.0,13.0,13.0"/>
    <t1 m="i183,10.0,19.0,1990" d="10.0,n4,15.0,16.0,16.0,17.0,18.0,18.0,19.0,19.0,19.0,19.0,18.0"/>
    <t1 m="i4,2.0,2.0,1990" d="2.0,n4,2.0,2.0,2.0,2.0,2.0,2.0,2.0,2.0,2.0,2.0,2.0"/>
    <t1 m="i132,38.0,45.0,1990" d="40.0,n4,39.0,38.0,39.0,39.0,40.0,40.0,41.0,43.0,42.0,43.0,45.0"/>
    <t1 m="i239,0.0,1.0,1990" d="1.0,n4,1.0,1.0,1.0,1.0,1.0,1.0,1.0,1.0,0.0,0.0,0.0"/>
    <t1 m="i22,4.0,10.0,1990" d="10.0,n4,9.0,4.0,7.0,7.0,8.0,6.0,4.0,4.0,5.0,8.0,5.0"/>
    <t1 m="i48,7.0,15.0,1990" d="15.0,n4,10.0,10.0,11.0,9.0,10.0,8.0,8.0,8.0,8.0,7.0,7.0"/>
    <t1 m="i196,5.0,6.0,1990" d="5.0,n4,5.0,5.0,5.0,6.0,6.0,5.0,5.0,5.0,5.0,5.0,5.0"/>
    <t1 m="i174,11.0,14.0,1990" d="14.0,n4,13.0,11.0,14.0,14.0,14.0,13.0,13.0,13.0,13.0,13.0,12.0"/>
    <t1 m="i219,4.0,8.0,1990" d="8.0,n4,6.0,6.0,6.0,6.0,6.0,5.0,5.0,5.0,4.0,4.0,4.0"/>
    <t1 m="i105,1.0,2.0,1990" d="2.0,n4,2.0,1.0,2.0,2.0,1.0,2.0,1.0,1.0,1.0,1.0,1.0"/>
    <t1 m="i47,7.0,11.0,1990" d="11.0,n4,9.0,9.0,9.0,9.0,8.0,7.0,8.0,8.0,8.0,7.0,7.0"/>
    <t1 m="i218,1.0,2.0,1990" d="2.0,n4,1.0,1.0,1.0,1.0,1.0,1.0,1.0,1.0,1.0,1.0,1.0"/>
    <t1 m="i244,6.0,21.0,1990" d="21.0,n4,17.0,15.0,11.0,14.0,11.0,7.0,6.0,10.0,9.0,6.0,10.0"/>
    <t1 m="i134,16.0,23.0,1990" d="22.0,n4,19.0,18.0,23.0,22.0,22.0,17.0,17.0,17.0,16.0,16.0,16.0"/>
    <t1 m="i3,3.0,5.0,1990" d="4.0,n4,5.0,5.0,5.0,5.0,5.0,4.0,4.0,4.0,4.0,4.0,3.0"/>
    <t1 m="i209,64.0,154.0,1990" d="64.0,n4,119.0,135.0,147.0,154.0,133.0,147.0,141.0,102.0,90.0,73.0,71.0"/>
    <t1 m="i194,1.0,1.0,1990" d="1.0,n4,1.0,1.0,1.0,1.0,1.0,1.0,1.0,1.0,1.0,1.0,1.0"/>
    <t1 m="i14,1.0,2.0,1990" d="2.0,n4,2.0,2.0,2.0,2.0,1.0,1.0,1.0,1.0,1.0,1.0,1.0"/>
    <t1 m="i5,1.0,3.0,1990" d="3.0,n4,2.0,2.0,1.0,2.0,1.0,2.0,2.0,2.0,2.0,1.0,1.0"/>
    <t1 m="i146,0.0,0.0,1990" d="0.0,n4,0.0,0.0,0.0,0.0,0.0,0.0,0.0,0.0,0.0,0.0,0.0"/>
    <t1 m="i140,61.0,77.0,1990" d="67.0,n4,68.0,66.0,66.0,71.0,72.0,74.0,75.0,76.0,77.0,61.0,69.0"/>
    <t1 m="i99,3.0,7.0,1990" d="6.0,n4,6.0,7.0,6.0,6.0,5.0,5.0,4.0,4.0,4.0,3.0,3.0"/>
    <t1 m="i24,1.0,1.0,1990" d="1.0,n4,1.0,1.0,1.0,1.0,1.0,1.0,1.0,1.0,1.0,1.0,1.0"/>
    <t1 m="i141,11.0,14.0,1990" d="14.0,n4,12.0,13.0,13.0,12.0,11.0,11.0,11.0,11.0,11.0,11.0,11.0"/>
    <t1 m="i10,5.0,10.0,1990" d="10.0,n4,8.0,8.0,7.0,7.0,7.0,7.0,6.0,6.0,6.0,6.0,5.0"/>
    <t1 m="i178,4.0,8.0,1990" d="8.0,n4,7.0,7.0,6.0,6.0,5.0,5.0,4.0,4.0,4.0,4.0,4.0"/>
    <t1 m="i226,8.0,12.0,1990" d="9.0,n4,8.0,12.0,12.0,12.0,12.0,12.0,12.0,12.0,12.0,12.0,12.0"/>
    <t1 m="i81,7.0,14.0,1990" d="7.0,n4,10.0,10.0,13.0,12.0,13.0,14.0,14.0,14.0,14.0,13.0,11.0"/>
    <t1 m="i32,4.0,6.0,1990" d="4.0,n4,5.0,5.0,6.0,6.0,5.0,5.0,6.0,6.0,5.0,5.0,5.0"/>
    <t1 m="i82,1.0,2.0,1990" d="2.0,n4,2.0,2.0,1.0,1.0,1.0,1.0,1.0,1.0,1.0,1.0,1.0"/>
    <t1 m="i168,1.0,1.0,1990" d="1.0,n4,1.0,1.0,1.0,1.0,1.0,1.0,1.0,1.0,1.0,1.0,1.0"/>
    <t1 m="i110,4.0,7.0,1990" d="7.0,n4,6.0,5.0,5.0,5.0,4.0,4.0,4.0,4.0,4.0,4.0,4.0"/>
    <t1 m="i237,2.0,3.0,1990" d="3.0,n4,3.0,2.0,2.0,2.0,2.0,2.0,2.0,2.0,2.0,2.0,2.0"/>
    <t1 m="i55,1.0,3.0,1990" d="3.0,n4,2.0,2.0,2.0,2.0,1.0,1.0,1.0,1.0,1.0,1.0,1.0"/>
    <t1 m="i154,18.0,33.0,1990" d="33.0,n4,27.0,27.0,26.0,26.0,25.0,21.0,22.0,21.0,22.0,21.0,18.0"/>
    <t1 m="i52,1.0,4.0,1990" d="4.0,n4,3.0,2.0,2.0,2.0,2.0,2.0,2.0,2.0,1.0,1.0,1.0"/>
    <t1 m="i221,12.0,38.0,1990" d="22.0,n4,12.0,16.0,16.0,19.0,20.0,22.0,26.0,29.0,31.0,35.0,38.0"/>
    <t1 m="i212,8.0,10.0,1990" d="10.0,n4,10.0,10.0,9.0,9.0,9.0,10.0,10.0,9.0,9.0,9.0,8.0"/>
    <t1 m="i101,29.0,44.0,1990" d="42.0,n4,43.0,43.0,43.0,44.0,42.0,42.0,39.0,37.0,34.0,30.0,29.0"/>
    <t1 m="i112,1.0,1.0,1990" d="1.0,n4,1.0,1.0,1.0,1.0,1.0,1.0,1.0,1.0,1.0,1.0,1.0"/>
    <t1 m="i197,43.0,54.0,1990" d="43.0,n4,43.0,43.0,45.0,47.0,50.0,49.0,50.0,52.0,52.0,54.0,54.0"/>
    <t1 m="i68,48.0,69.0,1990" d="61.0,n4,66.0,67.0,67.0,67.0,48.0,49.0,64.0,66.0,61.0,65.0,69.0"/>
    <t1 m="i153,61.0,127.0,1990" d="68.0,n4,127.0,61.0,65.0,67.0,76.0,81.0,75.0,82.0,65.0,77.0,77.0"/>
    <t1 m="i152,15.0,50.0,1990" d="50.0,n4,50.0,44.0,45.0,45.0,44.0,40.0,37.0,32.0,25.0,21.0,15.0"/>
    <t1 m="i243,3.0,14.0,1990" d="14.0,n4,12.0,10.0,10.0,10.0,10.0,11.0,10.0,7.0,4.0,3.0,7.0"/>
    <t1 m="i240,3.0,4.0,1990" d="4.0,n4,3.0,3.0,3.0,3.0,3.0,3.0,3.0,3.0,3.0,3.0,3.0"/>
    <t1 m="i126,1.0,4.0,1990" d="4.0,n4,4.0,4.0,4.0,4.0,2.0,2.0,2.0,2.0,1.0,1.0,1.0"/>
    <t1 m="i6,2.0,4.0,1990" d="4.0,n4,3.0,2.0,2.0,3.0,3.0,2.0,2.0,2.0,2.0,2.0,2.0"/>
    <t1 m="i185,43.0,93.0,1990" d="43.0,n4,67.0,71.0,73.0,75.0,79.0,86.0,91.0,93.0,93.0,93.0,91.0"/>
    <t1 m="i188,1.0,2.0,1990" d="2.0,n4,2.0,2.0,2.0,1.0,1.0,2.0,2.0,2.0,2.0,2.0,2.0"/>
    <t1 m="i189,2.0,4.0,1990" d="4.0,n4,3.0,3.0,2.0,2.0,2.0,3.0,2.0,2.0,2.0,2.0,2.0"/>
    <t1 m="i216,80.0,368.0,1990" d="80.0,n4,114.0,129.0,166.0,201.0,274.0,318.0,368.0,234.0,243.0,267.0,304.0"/>
    <t1 m="i29,8.0,13.0,1990" d="13.0,n4,11.0,11.0,10.0,10.0,10.0,10.0,9.0,9.0,9.0,8.0,8.0"/>
    <t1 m="i245,5.0,6.0,1990" d="6.0,n4,6.0,6.0,6.0,6.0,6.0,6.0,6.0,6.0,6.0,6.0,5.0"/>
    <t1 m="i199,5.0,10.0,1990" d="10.0,n4,9.0,8.0,8.0,8.0,6.0,6.0,5.0,5.0,5.0,5.0,5.0"/>
    <t1 m="i181,6.0,8.0,1990" d="6.0,n4,8.0,7.0,7.0,7.0,7.0,7.0,7.0,6.0,6.0,6.0,6.0"/>
    <t1 m="i234,55.0,105.0,1990" d="105.0,n4,81.0,79.0,76.0,77.0,77.0,73.0,70.0,70.0,62.0,60.0,55.0"/>
    <t1 m="i211,3.0,5.0,1990" d="5.0,n4,5.0,4.0,4.0,4.0,4.0,3.0,3.0,3.0,3.0,3.0,3.0"/>
    <t1 m="i171,4.0,10.0,1990" d="6.0,n4,5.0,10.0,4.0,4.0,9.0,8.0,8.0,6.0,5.0,6.0,7.0"/>
    <t1 m="i107,1.0,1.0,1990" d="1.0,n4,1.0,1.0,1.0,1.0,1.0,1.0,1.0,1.0,1.0,1.0,1.0"/>
    <t1 m="i25,19.0,40.0,1990" d="40.0,n4,30.0,29.0,28.0,26.0,25.0,24.0,23.0,22.0,21.0,20.0,19.0"/>
    <t1 m="i15,5.0,11.0,1990" d="5.0,n4,7.0,8.0,8.0,9.0,9.0,10.0,10.0,10.0,11.0,10.0,10.0"/>
    <t1 m="i155,23.0,51.0,1990" d="51.0,n4,45.0,43.0,41.0,39.0,32.0,28.0,28.0,26.0,25.0,24.0,23.0"/>
    <t1 m="i249,23.0,41.0,1990" d="41.0,n4,31.0,28.0,25.0,25.0,24.0,24.0,24.0,23.0,23.0,23.0,23.0"/>
    <t1 m="i71,31.0,73.0,1990" d="31.0,n4,57.0,59.0,60.0,63.0,67.0,67.0,70.0,72.0,73.0,72.0,73.0"/>
    <t1 m="i97,8.0,18.0,1990" d="17.0,n4,15.0,18.0,18.0,14.0,13.0,8.0,9.0,9.0,12.0,13.0,12.0"/>
    <t1 m="i13,1.0,1.0,1990" d="1.0,n4,1.0,1.0,1.0,1.0,1.0,1.0,1.0,1.0,1.0,1.0,1.0"/>
    <t1 m="i156,1.0,1.0,1990" d="1.0,n4,1.0,1.0,1.0,1.0,1.0,1.0,1.0,1.0,1.0,1.0,1.0"/>
    <t1 m="i167,6.0,21.0,1990" d="21.0,n4,18.0,14.0,16.0,13.0,16.0,6.0,11.0,11.0,12.0,11.0,11.0"/>
    <t1 m="i158,3.0,15.0,1990" d="15.0,n4,9.0,8.0,10.0,9.0,6.0,5.0,5.0,4.0,5.0,4.0,3.0"/>
    <t1 m="i207,40.0,115.0,1990" d="115.0,n4,96.0,87.0,83.0,81.0,78.0,75.0,67.0,64.0,58.0,46.0,40.0"/>
    <t1 m="i9,1.0,1.0,1990" d="1.0,n4,1.0,1.0,1.0,1.0,1.0,1.0,1.0,1.0,1.0,1.0,1.0"/>
    <t1 m="i40,38.0,106.0,1990" d="38.0,n4,70.0,54.0,82.0,87.0,92.0,97.0,95.0,86.0,105.0,106.0,91.0"/>
    <t1 m="i75,1.0,2.0,1990" d="2.0,n4,1.0,1.0,1.0,1.0,1.0,1.0,1.0,1.0,1.0,1.0,1.0"/>
    <t1 m="i128,5.0,11.0,1990" d="5.0,n4,8.0,9.0,10.0,11.0,11.0,10.0,10.0,10.0,9.0,9.0,7.0"/>
    <t1 m="i214,13.0,19.0,1990" d="19.0,n4,17.0,16.0,16.0,16.0,15.0,15.0,15.0,14.0,14.0,14.0,13.0"/>
    <t1 m="i109,1.0,1.0,1990" d="1.0,n4,1.0,1.0,1.0,1.0,1.0,1.0,1.0,1.0,1.0,1.0,1.0"/>
    <t1 m="i238,1.0,1.0,1990" d="1.0,n4,1.0,1.0,1.0,1.0,1.0,1.0,1.0,1.0,1.0,1.0,1.0"/>
    <t1 m="i87,1.0,1.0,1990" d="1.0,n4,1.0,1.0,1.0,1.0,1.0,1.0,1.0,1.0,1.0,1.0,1.0"/>
    <t1 m="i204,3.0,7.0,1990" d="7.0,n4,7.0,6.0,5.0,5.0,5.0,4.0,4.0,4.0,3.0,3.0,3.0"/>
    <t1 m="i203,3.0,6.0,1990" d="6.0,n4,5.0,5.0,5.0,5.0,5.0,4.0,4.0,4.0,3.0,3.0,3.0"/>
    <t1 m="i93,38.0,54.0,1990" d="41.0,n4,42.0,45.0,50.0,53.0,54.0,40.0,41.0,45.0,43.0,38.0,40.0"/>
    <t1 m="i28,37.0,94.0,1990" d="37.0,n4,56.0,64.0,74.0,80.0,79.0,83.0,90.0,84.0,94.0,88.0,88.0"/>
    <t1 m="i113,8.0,20.0,1990" d="8.0,n4,8.0,10.0,12.0,15.0,17.0,18.0,19.0,18.0,20.0,20.0,19.0"/>
  </data>
</indicator>